django_unittest_helper/__init__.py
django_unittest_helper/image.py
django_unittest_helper/random_generator.py
django_unittest_helper-0.3.dist-info/LICENSE
django_unittest_helper-0.3.dist-info/METADATA
django_unittest_helper-0.3.dist-info/WHEEL
django_unittest_helper-0.3.dist-info/top_level.txt
django_unittest_helper-0.3.dist-info/RECORD
