Metadata-Version: 2.1
Name: django-unittest-helper
Version: 0.3
Summary: Helper package for django unittest
Home-page: https://github.com/masudurHimel/django_unittest_helper
Author: Md. Masudur Rahman
Author-email: masudurhimel@gmail.com
License: MIT
Download-URL: https://github.com/masudurHimel/django_unittest_helper/archive/refs/tags/v_03.tar.gz
Keywords: django,unittest
Platform: UNKNOWN
Classifier: Development Status :: 3 - Alpha
Classifier: Intended Audience :: Developers
Classifier: Topic :: Software Development :: Build Tools
Classifier: License :: OSI Approved :: MIT License
Classifier: Programming Language :: Python :: 3
License-File: LICENSE
Requires-Dist: Pillow
